nftsets/__init__.py
nftsets/_cli.py
nftsets/attributes.py
nftsets/config.py
nftsets/create.py
nftsets/manager.py
nftsets/py.typed
nftsets/typing.py
nftsets/version.py
nftsets-0.1.0b0.dist-info/LICENSE
nftsets-0.1.0b0.dist-info/METADATA
nftsets-0.1.0b0.dist-info/WHEEL
nftsets-0.1.0b0.dist-info/entry_points.txt
nftsets-0.1.0b0.dist-info/top_level.txt
nftsets-0.1.0b0.dist-info/RECORD
